dolomite/__init__.py
dolomite-0.1.0.dist-info/LICENSE.txt
dolomite-0.1.0.dist-info/METADATA
dolomite-0.1.0.dist-info/WHEEL
dolomite-0.1.0.dist-info/top_level.txt
dolomite-0.1.0.dist-info/RECORD
