Metadata-Version: 2.1
Name: dolomite
Version: 0.1.0
Summary: Wrapper package for all dolomite-* packages.
Home-page: https://github.com/ArtifactDB/dolomite
Author: Jayaram Kancherla
Author-email: jayaram.kancherla@gmail.com
License: MIT
Project-URL: Documentation, https://github.com/ArtifactDB/dolomite
Platform: any
Classifier: Development Status :: 4 - Beta
Classifier: Programming Language :: Python
Requires-Python: >=3.8
License-File: LICENSE.txt
Requires-Dist: dolomite-base
Requires-Dist: dolomite-matrix
Requires-Dist: dolomite-ranges
Requires-Dist: dolomite-se
Requires-Dist: dolomite-sce
Requires-Dist: dolomite-mae
Requires-Dist: importlib-metadata ; python_version < "3.8"
Provides-Extra: testing
Requires-Dist: setuptools ; extra == 'testing'
Requires-Dist: pytest ; extra == 'testing'
Requires-Dist: pytest-cov ; extra == 'testing'
